tests/__init__.py
tests/mixer_tests.py
tests/randr_screen_tests.py
tests/test_config.py
tests/test_corner.py
tests/tracker_tests.py
tests/util.py
tests/xinput2_tracker_tests.py
volcorner/__init__.py
volcorner/config.py
volcorner/corner.py
volcorner/logging.py
volcorner/mixer.py
volcorner/rect.py
volcorner/screen.py
volcorner/signals.py
volcorner/tracker.py
volcorner/ui.py
volcorner/alsa/__init__.py
volcorner/alsa/alsamixer.py
volcorner/alsa/mixercffi.py
volcorner/images/background.png
volcorner/images/segment_empty0.png
volcorner/images/segment_empty1.png
volcorner/images/segment_empty2.png
volcorner/images/segment_empty3.png
volcorner/images/segment_empty4.png
volcorner/images/segment_full0.png
volcorner/images/segment_full1.png
volcorner/images/segment_full2.png
volcorner/images/segment_full3.png
volcorner/images/segment_full4.png
volcorner/images/segments.json
volcorner/qt/__init__.py
volcorner/qt/qtui.py
volcorner/scripts/__init__.py
volcorner/scripts/main.py
volcorner/x11/__init__.py
volcorner/x11/randrscreen.py
volcorner/x11/x11emptyui.py
volcorner/x11/xinput2tracker.py
volcorner-0.3.1.dist-info/DESCRIPTION.rst
volcorner-0.3.1.dist-info/METADATA
volcorner-0.3.1.dist-info/RECORD
volcorner-0.3.1.dist-info/WHEEL
volcorner-0.3.1.dist-info/entry_points.txt
volcorner-0.3.1.dist-info/metadata.json
volcorner-0.3.1.dist-info/top_level.txt
