Metadata-Version: 2.0
Name: volcorner
Version: 0.3.1
Summary: Volume hot corner utility
Home-page: https://github.com/cknave/volcorner
Author: kvance
Author-email: kvance@kvance.com
License: GNU General Public License v3 or later (GPLv3+)
Keywords: volume hot corner hotcorner
Platform: UNKNOWN
Classifier: Development Status :: 3 - Alpha
Classifier: Environment :: X11 Applications
Classifier: Intended Audience :: End Users/Desktop
Classifier: License :: OSI Approved :: GNU General Public License v3 or later (GPLv3+)
Classifier: Operating System :: POSIX :: Linux
Classifier: Programming Language :: Python :: 3
Classifier: Topic :: Multimedia :: Sound/Audio
Requires-Dist: appdirs
Requires-Dist: cffi
Requires-Dist: pyqt5
Requires-Dist: quamash
Requires-Dist: smokesignal
Requires-Dist: xcffib (>0.4.1)
